LICENSE
README.md
setup.cfg
setup.py
vectortween/Animation.py
vectortween/BezierCurveAnimation.py
vectortween/ColorAnimation.py
vectortween/Mapping.py
vectortween/NumberAnimation.py
vectortween/ParallelAnimation.py
vectortween/ParametricAnimation.py
vectortween/PauseAnimation.py
vectortween/PointAnimation.py
vectortween/PolarAnimation.py
vectortween/SequentialAnimation.py
vectortween/SumAnimation.py
vectortween/TimeConversion.py
vectortween/Tween.py
vectortween/Utils.py
vectortween/__init__.py
vectortween.egg-info/PKG-INFO
vectortween.egg-info/SOURCES.txt
vectortween.egg-info/dependency_links.txt
vectortween.egg-info/requires.txt
vectortween.egg-info/top_level.txt